dialtone/__init__.py
dialtone/config.py
dialtone/dialtone/async_dialtone.py
dialtone/dialtone/dialtone.py
dialtone/dialtone/dialtone_base.py
dialtone/errors.py
dialtone/types.py
dialtone/utils/api.py
dialtone/utils/prepare_payload.py
dialtone-0.0.39.dist-info/LICENSE
dialtone-0.0.39.dist-info/METADATA
dialtone-0.0.39.dist-info/WHEEL
dialtone-0.0.39.dist-info/RECORD
