Metadata-Version: 2.1
Name: dialtone
Version: 0.0.39
Summary: Dialtone
License: Apache-2.0
Author: Petr Gazarov
Author-email: petr@usedialtone.com
Requires-Python: >=3.9,<4.0
Classifier: License :: OSI Approved :: Apache Software License
Classifier: Programming Language :: Python :: 3
Classifier: Programming Language :: Python :: 3.9
Classifier: Programming Language :: Python :: 3.10
Classifier: Programming Language :: Python :: 3.11
Classifier: Programming Language :: Python :: 3.12
Requires-Dist: httpx (>=0.27.0,<0.28.0)
Requires-Dist: pydantic (>=2.7.4,<3.0.0)
